easyml/__init__.py
easyml/api.py
easyml/train.py
easyml_ai-0.1.1.dist-info/LICENSE
easyml_ai-0.1.1.dist-info/METADATA
easyml_ai-0.1.1.dist-info/WHEEL
easyml_ai-0.1.1.dist-info/top_level.txt
easyml_ai-0.1.1.dist-info/RECORD
