Metadata-Version: 2.2
Name: easyml-ai
Version: 0.1.1
Summary: A one-liner ML training and deployment library
Home-page: https://github.com/alexiisjbaptiste/easyml
Author: Alexis Jean Baptiste
Author-email: your.email@example.com
Classifier: Programming Language :: Python :: 3
Classifier: License :: OSI Approved :: MIT License
Classifier: Operating System :: OS Independent
Requires-Python: >=3.7
License-File: LICENSE
Requires-Dist: pandas
Requires-Dist: scikit-learn
Requires-Dist: xgboost
Requires-Dist: fastapi
Requires-Dist: uvicorn
Requires-Dist: joblib
Dynamic: author
Dynamic: author-email
Dynamic: classifier
Dynamic: home-page
Dynamic: requires-dist
Dynamic: requires-python
Dynamic: summary
